{
  "project_info": {
    "project_number": "704874734316",
    "project_id": "diary-app-7c11a",
    "storage_bucket": "diary-app-7c11a.appspot.com"
  },
  "client": [
    {
      "client_info": {
        "mobilesdk_app_id": "1:704874734316:android:5ac006b1efa74ccccd3bc9",
        "android_client_info": {
          "package_name": "com.example.diaryapp"
        }
      },
      "oauth_client": [
        {
          "client_id": "704874734316-aq0iokmiliafjkoaqrf9jnjpln8krjrk.apps.googleusercontent.com",
          "client_type": 3
        }
      ],
      "api_key": [
        {
          "current_key": "AIzaSyDd2T642Od9Y1b5ri2ZONOvzF2Dpa4NLio"
        }
      ],
      "services": {
        "appinvite_service": {
          "other_platform_oauth_client": [
            {
              "client_id": "704874734316-aq0iokmiliafjkoaqrf9jnjpln8krjrk.apps.googleusercontent.com",
              "client_type": 3
            }
          ]
        }
      }
    }
  ],
  "configuration_version": "1"
}